minecraftstatus/__init__.py
minecraftstatus/client.py
minecraftstatus/errors.py
minecraftstatus/http.py
minecraftstatus/server_status.py
minecraftstatus-0.1.0.dist-info/LICENSE
minecraftstatus-0.1.0.dist-info/METADATA
minecraftstatus-0.1.0.dist-info/WHEEL
minecraftstatus-0.1.0.dist-info/RECORD
