Metadata-Version: 2.1
Name: minecraftstatus
Version: 0.1.0
Summary: minecraftstatus is an asynchronous wrapper for https://api.iapetus11.me.
Home-page: https://github.com/Infernum1/minecraftstatus
License: MIT
Keywords: minecraft,api,wrapper,asynchronous,server
Author: Infernum1
Requires-Python: >3.6
Classifier: License :: OSI Approved :: MIT License
Classifier: Operating System :: OS Independent
Classifier: Programming Language :: Python :: 3
Classifier: Programming Language :: Python :: 3.7
Classifier: Programming Language :: Python :: 3.8
Classifier: Programming Language :: Python :: 3.9
Classifier: Programming Language :: Python :: 3.10
Classifier: Programming Language :: Python :: 3.11
Requires-Dist: aiohttp (>=3.7.2,<4.0.0)
Project-URL: Documentation, https://infernum1.github.io/minecraftstatus/
Project-URL: Repository, https://github.com/Infernum1/minecraftstatus
